{
  "project_info": {
    "project_number": "176097130446",
    "project_id": "fertilizer-recommendatio-73585",
    "storage_bucket": "fertilizer-recommendatio-73585.appspot.com"
  },
  "client": [
    {
      "client_info": {
        "mobilesdk_app_id": "1:176097130446:android:d42d157eb292f516e8dd9f",
        "android_client_info": {
          "package_name": "com.example.fertilizer_recommendation_system"
        }
      },
      "oauth_client": [
        {
          "client_id": "176097130446-86rarh5chq6aheuljb1t93rqflj1oaum.apps.googleusercontent.com",
          "client_type": 3
        }
      ],
      "api_key": [
        {
          "current_key": "AIzaSyDThrn2rvat0SjgOwAMefkj80tEgFQyvPg"
        }
      ],
      "services": {
        "appinvite_service": {
          "other_platform_oauth_client": [
            {
              "client_id": "176097130446-86rarh5chq6aheuljb1t93rqflj1oaum.apps.googleusercontent.com",
              "client_type": 3
            }
          ]
        }
      }
    }
  ],
  "configuration_version": "1"
}